basic_calculator/__init__.py
basic_calculator/calculator.py
basic_calculator_sarif-0.1.0.dist-info/licenses/LICENSE
basic_calculator_sarif-0.1.0.dist-info/METADATA
basic_calculator_sarif-0.1.0.dist-info/WHEEL
basic_calculator_sarif-0.1.0.dist-info/top_level.txt
basic_calculator_sarif-0.1.0.dist-info/RECORD
